transmogrifydict.py
transmogrifydict-1.1.3.post1.dist-info/LICENSE
transmogrifydict-1.1.3.post1.dist-info/METADATA
transmogrifydict-1.1.3.post1.dist-info/WHEEL
transmogrifydict-1.1.3.post1.dist-info/top_level.txt
transmogrifydict-1.1.3.post1.dist-info/RECORD
