Metadata-Version: 2.1
Name: transmogrifydict
Version: 1.1.3.post1
Summary: The "turn a dict from one API into a dict for another" python module.
Home-page: https://github.com/arrai-innovations/transmogrifydict
Author: Arrai Innovations
Author-email: support@arrai.com
License: UNKNOWN
Platform: UNKNOWN
Classifier: Development Status :: 5 - Production/Stable
Classifier: Programming Language :: Python :: 2
Classifier: Programming Language :: Python :: 2.7
Classifier: Programming Language :: Python :: 3
Classifier: Programming Language :: Python :: 3.5
Classifier: Programming Language :: Python :: 3.6
Classifier: Programming Language :: Python :: 3.7
Classifier: Programming Language :: Python :: 3.8
Classifier: License :: OSI Approved :: BSD License
Classifier: Intended Audience :: Developers
Requires-Dist: six (<2.0.0,>=1.10.0)
